pseudo_random/__init__.py
pseudo_random/pseudo_random.py
pseudo_random-0.0.2.dist-info/AUTHORS.rst
pseudo_random-0.0.2.dist-info/LICENSE
pseudo_random-0.0.2.dist-info/METADATA
pseudo_random-0.0.2.dist-info/WHEEL
pseudo_random-0.0.2.dist-info/top_level.txt
pseudo_random-0.0.2.dist-info/RECORD
